{"transfers_out": 20822, "yellow_cards": 0, "code": 8597, "event_total": 0, "goals_conceded": 0, "photo": "8597.jpg", "red_cards": 0, "saves": 0, "ep_this": "0.3", "value_form": "0.1", "next_fixture": "Man Utd (H)", "team_id": 1, "goals_scored": 0, "web_name": "Rosicky", "value_season": "0.6", "fixtures": {"all": [["22 Nov 17:30", "Gameweek 12", "Man Utd (H)"], ["29 Nov 12:45", "Gameweek 13", "West Brom (A)"], ["03 Dec 19:45", "Gameweek 14", "Southampton (H)"], ["06 Dec 15:00", "Gameweek 15", "Stoke (A)"], ["13 Dec 17:30", "Gameweek 16", "Newcastle (H)"], ["21 Dec 16:00", "Gameweek 17", "Liverpool (A)"], ["26 Dec 17:30", "Gameweek 18", "QPR (H)"], ["28 Dec 15:00", "Gameweek 19", "West Ham (A)"], ["01 Jan 15:00", "Gameweek 20", "Southampton (A)"], ["10 Jan 15:00", "Gameweek 21", "Stoke (H)"], ["17 Jan 15:00", "Gameweek 22", "Man City (A)"], ["31 Jan 15:00", "Gameweek 23", "Aston Villa (H)"], ["07 Feb 15:00", "Gameweek 24", "Spurs (A)"], ["10 Feb 19:45", "Gameweek 25", "Leicester (H)"], ["21 Feb 15:00", "Gameweek 26", "Crystal Palace (A)"], ["28 Feb 15:00", "Gameweek 27", "Everton (H)"], ["03 Mar 19:45", "Gameweek 28", "QPR (A)"], ["14 Mar 15:00", "Gameweek 29", "West Ham (H)"], ["21 Mar 15:00", "Gameweek 30", "Newcastle (A)"], ["04 Apr 15:00", "Gameweek 31", "Liverpool (H)"], ["11 Apr 15:00", "Gameweek 32", "Burnley (A)"], ["18 Apr 15:00", "Gameweek 33", "Sunderland (H)"], ["25 Apr 15:00", "Gameweek 34", "Chelsea (H)"], ["02 May 15:00", "Gameweek 35", "Hull (A)"], ["09 May 15:00", "Gameweek 36", "Swansea (H)"], ["16 May 15:00", "Gameweek 37", "Man Utd (A)"], ["24 May 15:00", "Gameweek 38", "West Brom (H)"]], "summary": [[12, "MUN (H)", "22 Nov 17:30"], [13, "WBA (A)", "29 Nov 12:45"], [14, "SOU (H)", "03 Dec 19:45"]]}, "team_code": 3, "id": 13, "special": false, "first_name": "Tomas", "transfers_out_event": 58, "chance_of_playing_next_round": 100, "team_name": "Arsenal", "cost_change_event_fall": 0, "event_explain": [["Minutes played", 0, 0]], "type_name": "Midfielder", "bps": 9, "cost_change_start_fall": 2, "season_history": [["2006/07", 1826, 3, 3, 0, 17, 0, 0, 0, 3, 0, 0, 8, 0, 0, 86, 83], ["2007/08", 1334, 6, 2, 0, 9, 0, 0, 0, 1, 0, 0, 9, 0, 0, 76, 84], ["2008/09", 0, 0, 0, 0, 0, 0, 0, 0, 0, 0, 0, 0, 0, 0, 72, 0], ["2009/10", 1306, 3, 4, 0, 20, 0, 0, 0, 1, 0, 0, 0, 0, 0, 68, 69], ["2010/11", 939, 0, 1, 2, 17, 0, 0, 1, 3, 0, 0, 0, 0, 0, 60, 30], ["2011/12", 1762, 1, 4, 5, 32, 0, 0, 0, 4, 0, 0, 2, 265, 0, 58, 66], ["2012/13", 610, 2, 1, 3, 6, 0, 0, 0, 2, 0, 0, 3, 146, 0, 57, 34], ["2013/14", 1573, 2, 1, 11, 18, 0, 0, 0, 7, 0, 0, 5, 323, 77, 48, 66]], "total_points": 3, "penalties_missed": 0, "ea_index": 4, "status": "a", "form": "0.2", "own_goals": 0, "bonus": 0, "current_fixture": "Swansea (A)", "now_cost": 48, "fixture_history": {"all": [["16 Aug 17:30", 1, "CRY(H) 2-1", 0, 0, 0, 0, 0, 0, 0, 0, 0, 0, 0, 0, 0, 0, 0, 50, 0], ["23 Aug 17:30", 2, "EVE(A) 2-2", 0, 0, 0, 0, 0, 0, 0, 0, 0, 0, 0, 0, 0, 0, -4091, 50, 0], ["31 Aug 16:00", 3, "LEI(A) 1-1", 0, 0, 0, 0, 0, 0, 0, 0, 0, 0, 0, 0, 0, 0, -4196, 49, 0], ["13 Sep 12:45", 4, "MCI(H) 2-2", 0, 0, 0, 0, 0, 0, 0, 0, 0, 0, 0, 0, 0, 0, -3443, 49, 0], ["20 Sep 15:00", 5, "AVL(A) 3-0", 13, 0, 0, 0, 0, 0, 0, 0, 0, 0, 0, 0, 3, 3, -1732, 48, 1], ["27 Sep 17:30", 6, "TOT(H) 1-1", 0, 0, 0, 0, 0, 0, 0, 0, 0, 0, 0, 0, 0, 0, -925, 48, 0], ["05 Oct 14:05", 7, "CHE(A) 0-2", 8, 0, 0, 0, 0, 0, 0, 0, 0, 0, 0, 0, 1, 3, -847, 48, 1], ["18 Oct 15:00", 8, "HUL(H) 2-2", 0, 0, 0, 0, 0, 0, 0, 0, 0, 0, 0, 0, 0, 0, -1034, 48, 0], ["25 Oct 15:00", 9, "SUN(A) 2-0", 1, 0, 0, 0, 0, 0, 0, 0, 0, 0, 0, 0, 0, 3, -630, 48, 1], ["01 Nov 15:00", 10, "BUR(H) 3-0", 0, 0, 0, 0, 0, 0, 0, 0, 0, 0, 0, 0, 0, 0, -397, 48, 0], ["09 Nov 16:00", 11, "SWA(A) 1-2", 0, 0, 0, 0, 0, 0, 0, 0, 0, 0, 0, 0, 0, 0, -397, 48, 0]], "summary": [[9, "SUN (A)", 1], [10, "BUR (H)", 0], [11, "SWA (A)", 0]]}, "clean_sheets": 0, "assists": 0, "selected_by_percent": "0.5", "transfers_in": 3087, "news": "", "dreamteam_count": 0, "penalties_saved": 0, "cost_change_start": -2, "in_dreamteam": false, "points_per_game": "1.0", "minutes": 22, "transfers_in_event": 15, "selected_by": "0.5", "element_type": 3, "ep_next": "0.3", "team": 1, "chance_of_playing_this_round": 100, "event_points": 0, "second_name": "Rosicky", "cost_change_event": 0}