{"transfers_out": 7848, "yellow_cards": 2, "code": 55459, "event_total": 9, "goals_conceded": 14, "photo": "55459.jpg", "red_cards": 0, "saves": 0, "ep_this": "5.5", "value_form": "1.0", "next_fixture": "Everton (A)", "team_id": 20, "goals_scored": 0, "web_name": "Cresswell", "value_season": "6.5", "fixtures": {"all": [["22 Nov 15:00", "Gameweek 12", "Everton (A)"], ["29 Nov 15:00", "Gameweek 13", "Newcastle (H)"], ["02 Dec 20:00", "Gameweek 14", "West Brom (A)"], ["07 Dec 13:30", "Gameweek 15", "Swansea (H)"], ["13 Dec 15:00", "Gameweek 16", "Sunderland (A)"], ["20 Dec 15:00", "Gameweek 17", "Leicester (H)"], ["26 Dec 12:45", "Gameweek 18", "Chelsea (A)"], ["28 Dec 15:00", "Gameweek 19", "Arsenal (H)"], ["01 Jan 15:00", "Gameweek 20", "West Brom (H)"], ["10 Jan 15:00", "Gameweek 21", "Swansea (A)"], ["17 Jan 15:00", "Gameweek 22", "Hull (H)"], ["31 Jan 15:00", "Gameweek 23", "Liverpool (A)"], ["07 Feb 15:00", "Gameweek 24", "Man Utd (H)"], ["10 Feb 19:45", "Gameweek 25", "Southampton (A)"], ["21 Feb 15:00", "Gameweek 26", "Spurs (A)"], ["28 Feb 15:00", "Gameweek 27", "Crystal Palace (H)"], ["03 Mar 19:45", "Gameweek 28", "Chelsea (H)"], ["14 Mar 15:00", "Gameweek 29", "Arsenal (A)"], ["21 Mar 15:00", "Gameweek 30", "Sunderland (H)"], ["04 Apr 15:00", "Gameweek 31", "Leicester (A)"], ["11 Apr 15:00", "Gameweek 32", "Stoke (H)"], ["18 Apr 15:00", "Gameweek 33", "Man City (A)"], ["25 Apr 15:00", "Gameweek 34", "QPR (A)"], ["02 May 15:00", "Gameweek 35", "Burnley (H)"], ["09 May 15:00", "Gameweek 36", "Aston Villa (A)"], ["16 May 15:00", "Gameweek 37", "Everton (H)"], ["24 May 15:00", "Gameweek 38", "Newcastle (A)"]], "summary": [[12, "EVE (A)", "22 Nov 15:00"], [13, "NEW (H)", "29 Nov 15:00"], [14, "WBA (A)", "02 Dec 20:00"]]}, "team_code": 21, "id": 506, "special": false, "first_name": "Aaron", "transfers_out_event": 105, "chance_of_playing_next_round": null, "team_name": "West Ham", "cost_change_event_fall": 0, "event_explain": [["Bonus", 3, 3], ["Clean sheets", 1, 4], ["Minutes played", 90, 2]], "type_name": "Defender", "bps": 169, "cost_change_start_fall": 1, "season_history": [], "total_points": 35, "penalties_missed": 0, "ea_index": 168, "status": "a", "form": "5.5", "own_goals": 0, "bonus": 5, "current_fixture": "Aston Villa (H)", "now_cost": 54, "fixture_history": {"all": [["16 Aug 15:00", 1, "TOT(H) 0-1", 90, 0, 0, 0, 1, 0, 0, 0, 0, 0, 0, 0, 6, 19, 0, 55, 2], ["23 Aug 15:00", 2, "CRY(A) 3-1", 90, 0, 0, 0, 1, 0, 0, 0, 0, 0, 0, 0, 16, 6, -162, 55, 2], ["30 Aug 15:00", 3, "SOU(H) 1-3", 90, 0, 0, 0, 3, 0, 0, 0, 1, 0, 0, 0, 8, 7, -787, 55, 0], ["15 Sep 20:00", 4, "HUL(A) 2-2", 90, 0, 0, 0, 2, 0, 0, 0, 0, 0, 0, 0, 13, 5, -1647, 55, 1], ["20 Sep 17:30", 5, "LIV(H) 3-1", 90, 0, 0, 0, 1, 0, 0, 0, 0, 0, 0, 0, 29, 9, -835, 55, 2], ["27 Sep 15:00", 6, "MUN(A) 1-2", 90, 0, 0, 0, 2, 0, 0, 0, 0, 0, 0, 0, 7, 17, -339, 54, 1], ["05 Oct 16:15", 7, "QPR(H) 2-0", 90, 0, 0, 1, 0, 0, 0, 0, 1, 0, 0, 0, 23, 14, 154, 54, 5], ["18 Oct 15:00", 8, "BUR(A) 3-1", 90, 0, 1, 0, 1, 0, 0, 0, 0, 0, 0, 2, 25, 36, 105, 54, 7], ["25 Oct 12:45", 9, "MCI(H) 2-1", 90, 0, 1, 0, 1, 0, 0, 0, 0, 0, 0, 0, 21, 19, 411, 54, 5], ["01 Nov 15:00", 10, "STK(A) 2-2", 90, 0, 0, 0, 2, 0, 0, 0, 0, 0, 0, 0, 6, 7, 7990, 54, 1], ["08 Nov 15:00", 11, "AVL(H) 0-0", 90, 0, 0, 1, 0, 0, 0, 0, 0, 0, 0, 3, 14, 30, 4052, 54, 9]], "summary": [[9, "MCI (H)", 5], [10, "STK (A)", 1], [11, "AVL (H)", 9]]}, "clean_sheets": 2, "assists": 2, "selected_by_percent": "0.7", "transfers_in": 17335, "news": "", "dreamteam_count": 1, "penalties_saved": 0, "cost_change_start": -1, "in_dreamteam": false, "points_per_game": "3.2", "minutes": 990, "transfers_in_event": 650, "selected_by": "0.7", "element_type": 2, "ep_next": "5.5", "team": 20, "chance_of_playing_this_round": null, "event_points": 9, "second_name": "Cresswell", "cost_change_event": 0}